pycoretools/__init__.py
pycoretools/concurrency.py
pycoretools/context.py
pycoretools/decorators.py
pycoretools/iterables.py
pycoretools/sentinels.py
pycoretools/version.py
pycoretools-0.1.0.dist-info/LICENSE.txt
pycoretools-0.1.0.dist-info/METADATA
pycoretools-0.1.0.dist-info/WHEEL
pycoretools-0.1.0.dist-info/top_level.txt
pycoretools-0.1.0.dist-info/RECORD
